setup.cfg
setup.py
bin/settler
settler/__init__.py
settler.egg-info/PKG-INFO
settler.egg-info/SOURCES.txt
settler.egg-info/dependency_links.txt
settler.egg-info/not-zip-safe
settler.egg-info/requires.txt
settler.egg-info/top_level.txt