Metadata-Version: 1.1
Name: settler
Version: 0.2
Summary: Make a fresh OS install feel like home!
Home-page: http://github.com/dulex123/settler
Author: Dusan Josipovic
Author-email: dusanix@gmail.com
License: MIT
Download-URL: https://github.com/dulex123/settler/archive/0.2.tar.gz
Keywords: dotfiles,settler,setup
Platform: UNKNOWN
